ttk_epay/__init__.py
ttk_epay/app.py
ttk_epay/models.py
ttk_epay/settings.py
test_ttk_epay-0.1.6.dist-info/LICENSE
test_ttk_epay-0.1.6.dist-info/METADATA
test_ttk_epay-0.1.6.dist-info/WHEEL
test_ttk_epay-0.1.6.dist-info/RECORD
